LICENSE
MANIFEST.in
Makefile
README.rst
setup.py
tox.ini
docs/Makefile
docs/__init__.py
docs/conf.py
docs/index.rst
docs/make.bat
docs/_build/doctrees/environment.pickle
docs/_build/doctrees/index.doctree
docs/_build/html/.buildinfo
docs/_build/html/genindex.html
docs/_build/html/index.html
docs/_build/html/objects.inv
docs/_build/html/search.html
docs/_build/html/searchindex.js
docs/_build/html/_sources/index.txt
docs/_build/html/_static/ajax-loader.gif
docs/_build/html/_static/basic.css
docs/_build/html/_static/comment-bright.png
docs/_build/html/_static/comment-close.png
docs/_build/html/_static/comment.png
docs/_build/html/_static/default.css
docs/_build/html/_static/doctools.js
docs/_build/html/_static/down-pressed.png
docs/_build/html/_static/down.png
docs/_build/html/_static/file.png
docs/_build/html/_static/jquery.js
docs/_build/html/_static/minus.png
docs/_build/html/_static/plus.png
docs/_build/html/_static/pygments.css
docs/_build/html/_static/searchtools.js
docs/_build/html/_static/sidebar.js
docs/_build/html/_static/underscore.js
docs/_build/html/_static/up-pressed.png
docs/_build/html/_static/up.png
docs/_build/html/_static/websupport.js
py3s3/__init__.py
py3s3/files.py
py3s3/storage.py
py3s3/tests.py
py3s3/utils.py
py3s3.egg-info/PKG-INFO
py3s3.egg-info/SOURCES.txt
py3s3.egg-info/dependency_links.txt
py3s3.egg-info/top_level.txt