Metadata-Version: 1.1
Name: py3s3
Version: 0.2.4
Summary: A bare bones package for uploading to and downloading from AWS S3 from within Python 3.3+
Home-page: http://github.com/logston/py3s3
Author: Paul Logston
Author-email: code@logston.me
License: Copyright (c) 2014, Paul Logston
